cdktf_cdktf_provider_mongodbatlas/__init__.py
cdktf_cdktf_provider_mongodbatlas/py.typed
cdktf_cdktf_provider_mongodbatlas/_jsii/__init__.py
cdktf_cdktf_provider_mongodbatlas/_jsii/provider-mongodbatlas@8.6.1.jsii.tgz
cdktf_cdktf_provider_mongodbatlas/access_list_api_key/__init__.py
cdktf_cdktf_provider_mongodbatlas/advanced_cluster/__init__.py
cdktf_cdktf_provider_mongodbatlas/alert_configuration/__init__.py
cdktf_cdktf_provider_mongodbatlas/api_key/__init__.py
cdktf_cdktf_provider_mongodbatlas/api_key_project_assignment/__init__.py
cdktf_cdktf_provider_mongodbatlas/auditing/__init__.py
cdktf_cdktf_provider_mongodbatlas/backup_compliance_policy/__init__.py
cdktf_cdktf_provider_mongodbatlas/cloud_backup_schedule/__init__.py
cdktf_cdktf_provider_mongodbatlas/cloud_backup_snapshot/__init__.py
cdktf_cdktf_provider_mongodbatlas/cloud_backup_snapshot_export_bucket/__init__.py
cdktf_cdktf_provider_mongodbatlas/cloud_backup_snapshot_export_job/__init__.py
cdktf_cdktf_provider_mongodbatlas/cloud_backup_snapshot_restore_job/__init__.py
cdktf_cdktf_provider_mongodbatlas/cloud_provider_access_authorization/__init__.py
cdktf_cdktf_provider_mongodbatlas/cloud_provider_access_setup/__init__.py
cdktf_cdktf_provider_mongodbatlas/cluster/__init__.py
cdktf_cdktf_provider_mongodbatlas/cluster_outage_simulation/__init__.py
cdktf_cdktf_provider_mongodbatlas/custom_db_role/__init__.py
cdktf_cdktf_provider_mongodbatlas/custom_dns_configuration_cluster_aws/__init__.py
cdktf_cdktf_provider_mongodbatlas/data_lake_pipeline/__init__.py
cdktf_cdktf_provider_mongodbatlas/data_mongodbatlas_access_list_api_key/__init__.py
cdktf_cdktf_provider_mongodbatlas/data_mongodbatlas_access_list_api_keys/__init__.py
cdktf_cdktf_provider_mongodbatlas/data_mongodbatlas_advanced_cluster/__init__.py
cdktf_cdktf_provider_mongodbatlas/data_mongodbatlas_advanced_clusters/__init__.py
cdktf_cdktf_provider_mongodbatlas/data_mongodbatlas_alert_configuration/__init__.py
cdktf_cdktf_provider_mongodbatlas-8.6.1.dist-info/LICENSE
cdktf_cdktf_provider_mongodbatlas-8.6.1.dist-info/METADATA
cdktf_cdktf_provider_mongodbatlas-8.6.1.dist-info/WHEEL
cdktf_cdktf_provider_mongodbatlas-8.6.1.dist-info/top_level.txt
cdktf_cdktf_provider_mongodbatlas-8.6.1.dist-info/RECORD
